pubdoc/__init__.py
pubdoc/__main__.py
pubdoc/__version__.py
pubdoc/app.py
pubdoc/pubdoc.py
pubdoc/publishers/__init__.py
pubdoc/publishers/dokuwiki.py
pubdoc-0.5.3.dist-info/LICENSE
pubdoc-0.5.3.dist-info/METADATA
pubdoc-0.5.3.dist-info/WHEEL
pubdoc-0.5.3.dist-info/entry_points.txt
pubdoc-0.5.3.dist-info/top_level.txt
pubdoc-0.5.3.dist-info/RECORD
