Metadata-Version: 2.1
Name: pubdoc
Version: 0.5.3
Summary: Make technical documentstion from data sets
Home-page: https://github.com/brobots-corporation/pubdoc
Author: Evgenii Alaev
Author-email: ev.alaev@yandex.ru
License: GPL-3.0
Project-URL: Bug Reports, https://github.com/brobots-corporation/pubdoc/issues
Project-URL: Source, https://github.com/brobots-corporation/pubdoc
Platform: UNKNOWN
Classifier: Development Status :: 4 - Beta
Classifier: Intended Audience :: Developers
Classifier: Natural Language :: Russian
Classifier: Operating System :: OS Independent
Classifier: License :: OSI Approved :: GNU General Public License v3 (GPLv3)
Classifier: Programming Language :: Python :: 3.6
Classifier: Programming Language :: Python :: 3.7
Classifier: Programming Language :: Python :: 3.8
Classifier: Topic :: Software Development :: Libraries :: Python Modules
Requires-Python: >=3.6.0
Requires-Dist: Click (>=7.0)
Requires-Dist: dokuwiki (==1.2.1)
Requires-Dist: pprint (==0.1)
